.coveragerc
.gitignore
.travis.yml
CHANGELOG.rst
LICENSE.txt
MANIFEST.in
Makefile
README.rst
mktag
nose.cfg
requirements.txt
setup.cfg
setup.py
ci/rtd-requirements.txt
ci/test-requirements.txt
ci/travis.sh
debian/.gitignore
debian/changelog
debian/compat
debian/control
debian/rules
debian/watch
debian/source/format
doc/.gitignore
doc/Makefile
doc/source/aioswagger11.client.rst
doc/source/aioswagger11.rst
doc/source/conf.py
doc/source/index.rst
doc/source/modules.rst
doc/source/_static/.keep
doc/source/_templates/.keep
test-data/1.1/missing_resource/resources.json
test-data/1.1/simple/resources.json
test-data/1.1/simple/simple.json
tests/__init__.py
tests/client_test.py
tests/conftest.py
tests/http_client_test.py
tests/loader_test.py
tests/util_test.py
trio_swagger11/__init__.py
trio_swagger11/client.py
trio_swagger11/codegen.py
trio_swagger11/http_client.py
trio_swagger11/processors.py
trio_swagger11/swagger_model.py
trio_swagger11.egg-info/PKG-INFO
trio_swagger11.egg-info/SOURCES.txt
trio_swagger11.egg-info/dependency_links.txt
trio_swagger11.egg-info/entry_points.txt
trio_swagger11.egg-info/requires.txt
trio_swagger11.egg-info/top_level.txt